pygameplayer/__init__.py
pygameplayer/main.py
pygameplayer-1.0.2.dist-info/METADATA
pygameplayer-1.0.2.dist-info/WHEEL
pygameplayer-1.0.2.dist-info/top_level.txt
pygameplayer-1.0.2.dist-info/RECORD
