Metadata-Version: 2.1
Name: pygameplayer
Version: 1.0.2
Summary: A simple pygame player
Author: petteer
Classifier: Programming Language :: Python :: 3
Classifier: License :: OSI Approved :: MIT License
Classifier: Operating System :: OS Independent
Requires-Dist: pygame
